physicscore-0.2.1.0.dist-info/licenses/LICENSE
src/Competition.py
src/CompetitionFrame.py
src/GraphsFrame.py
src/JsonLoader.py
src/Physicscore.ico
src/Physicscore.py
src/PointsScrollFrame.py
src/ReportGenerator.py
src/ScrollableFrame.py
src/Var.py
src/__init__.py
physicscore-0.2.1.0.dist-info/METADATA
physicscore-0.2.1.0.dist-info/WHEEL
physicscore-0.2.1.0.dist-info/entry_points.txt
physicscore-0.2.1.0.dist-info/top_level.txt
physicscore-0.2.1.0.dist-info/RECORD
