Metadata-Version: 2.4
Name: Physicscore
Version: 0.2.1.0
Summary: An app for physics competitions in teams and their analysis
Home-page: https://github.com/AsrtoMichi/Physicscore
Download-URL: https://github.com/AsrtoMichi/Physicscore/archive/refs/heads/main.zip
Author: AsrtoMichi
Author-email: asrtomichi@gmail.com
Maintainer: AsrtoMichi
Maintainer-email: asrtomichi@gmail.com
License: GPLv3
Platform: Windows
Platform: Linux
Platform: Mac OS-X
Classifier: Development Status :: 3 - Alpha
Classifier: Intended Audience :: Education
Classifier: License :: OSI Approved :: GNU General Public License v3 (GPLv3)
Classifier: Programming Language :: Python :: 3.11
Classifier: Operating System :: OS Independent
Classifier: Topic :: Education
Requires-Python: >=3.6
License-File: LICENSE
Requires-Dist: matplotlib>=3.1.3
Dynamic: author
Dynamic: author-email
Dynamic: classifier
Dynamic: description
Dynamic: description-content-type
Dynamic: download-url
Dynamic: home-page
Dynamic: license
Dynamic: license-file
Dynamic: maintainer
Dynamic: maintainer-email
Dynamic: platform
Dynamic: requires-dist
Dynamic: requires-python
Dynamic: summary
